Changes.rst
LICENSE
MANIFEST.in
README.rst
bittray.png
setup.py
bittray/__init__.py
bittray/app.py
bittray/config.py
bittray/console_scripts.py
bittray/trayicon.py
bittray.egg-info/PKG-INFO
bittray.egg-info/SOURCES.txt
bittray.egg-info/dependency_links.txt
bittray.egg-info/entry_points.txt
bittray.egg-info/requires.txt
bittray.egg-info/top_level.txt