Metadata-Version: 1.1
Name: bittray
Version: 0.1.4
Summary: Bitcoin info in your systray
Home-page: http://github.com/nkuttler/bittray
Author: Nicolas Kuttler
Author-email: pypi@kuttler.eu
License: BSD
Keywords: bitcoin systray
Platform: UNKNOWN
Classifier: Development Status :: 3 - Alpha
Classifier: Intended Audience :: End Users/Desktop
Classifier: Programming Language :: Python
Classifier: Programming Language :: Python :: 2.7
